<?xml version="1.0" encoding="utf-8"?>
<TextureAtlas imagePath="skeebograbbed.png">
	<!-- Created with Adobe Animate version 20.5.0.29329 -->
	<!-- http://www.adobe.com/products/animate.html -->
	<SubTexture name="skeeboGRABBED0000" x="0" y="0" width="927" height="801" frameX="-248" frameY="-62" frameWidth="2214" frameHeight="863"/>
	<SubTexture name="skeeboGRABBED0001" x="931" y="0" width="927" height="801" frameX="-248" frameY="-62" frameWidth="2214" frameHeight="863"/>
	<SubTexture name="skeeboGRABBED0002" x="1862" y="0" width="834" height="801" frameX="-248" frameY="-62" frameWidth="2214" frameHeight="863"/>
	<SubTexture name="skeeboGRABBED0003" x="2700" y="0" width="655" height="724" frameX="-248" frameY="-139" frameWidth="2214" frameHeight="863"/>
	<SubTexture name="skeeboGRABBED0004" x="2700" y="0" width="655" height="724" frameX="-248" frameY="-139" frameWidth="2214" frameHeight="863"/>
	<SubTexture name="skeeboGRABBED0005" x="3359" y="0" width="611" height="724" frameX="-117" frameY="-28" frameWidth="2214" frameHeight="863"/>
	<SubTexture name="skeeboGRABBED0006" x="3359" y="0" width="611" height="724" frameX="-117" frameY="-28" frameWidth="2214" frameHeight="863"/>
	<SubTexture name="skeeboGRABBED0007" x="3974" y="0" width="612" height="723" frameX="-106" frameY="-12" frameWidth="2214" frameHeight="863"/>
	<SubTexture name="skeeboGRABBED0008" x="3974" y="0" width="612" height="723" frameX="-106" frameY="-12" frameWidth="2214" frameHeight="863"/>
	<SubTexture name="skeeboGRABBED0009" x="4590" y="0" width="613" height="723" frameX="-103" frameY="-9" frameWidth="2214" frameHeight="863"/>
	<SubTexture name="skeeboGRABBED0010" x="4590" y="0" width="613" height="723" frameX="-103" frameY="-9" frameWidth="2214" frameHeight="863"/>
	<SubTexture name="skeeboGRABBED0011" x="5207" y="0" width="612" height="726" frameX="-106" frameY="-4" frameWidth="2214" frameHeight="863"/>
	<SubTexture name="skeeboGRABBED0012" x="5207" y="0" width="612" height="726" frameX="-106" frameY="-4" frameWidth="2214" frameHeight="863"/>
	<SubTexture name="skeeboGRABBED0013" x="5823" y="0" width="612" height="727" frameX="-106" frameY="0" frameWidth="2214" frameHeight="863"/>
	<SubTexture name="skeeboGRABBED0014" x="6439" y="0" width="612" height="727" frameX="-106" frameY="0" frameWidth="2214" frameHeight="863"/>
	<SubTexture name="skeeboGRABBED0015" x="6439" y="0" width="612" height="727" frameX="-106" frameY="0" frameWidth="2214" frameHeight="863"/>
	<SubTexture name="skeeboGRABBED0016" x="7055" y="0" width="612" height="727" frameX="-106" frameY="0" frameWidth="2214" frameHeight="863"/>
	<SubTexture name="skeeboGRABBED0017" x="7055" y="0" width="612" height="727" frameX="-106" frameY="0" frameWidth="2214" frameHeight="863"/>
	<SubTexture name="skeeboGRABBED0018" x="0" y="805" width="612" height="727" frameX="-106" frameY="0" frameWidth="2214" frameHeight="863"/>
	<SubTexture name="skeeboGRABBED0019" x="0" y="805" width="612" height="727" frameX="-106" frameY="0" frameWidth="2214" frameHeight="863"/>
	<SubTexture name="skeeboGRABBED0020" x="616" y="805" width="612" height="727" frameX="-106" frameY="0" frameWidth="2214" frameHeight="863"/>
	<SubTexture name="skeeboGRABBED0021" x="1232" y="805" width="612" height="727" frameX="-106" frameY="0" frameWidth="2214" frameHeight="863"/>
	<SubTexture name="skeeboGRABBED0022" x="1848" y="805" width="612" height="727" frameX="-106" frameY="0" frameWidth="2214" frameHeight="863"/>
	<SubTexture name="skeeboGRABBED0023" x="2464" y="805" width="612" height="727" frameX="-106" frameY="0" frameWidth="2214" frameHeight="863"/>
	<SubTexture name="skeeboGRABBED0024" x="2464" y="805" width="612" height="727" frameX="-106" frameY="0" frameWidth="2214" frameHeight="863"/>
	<SubTexture name="skeeboGRABBED0025" x="2464" y="805" width="612" height="727" frameX="-106" frameY="0" frameWidth="2214" frameHeight="863"/>
	<SubTexture name="skeeboGRABBED0026" x="2464" y="805" width="612" height="727" frameX="-106" frameY="0" frameWidth="2214" frameHeight="863"/>
	<SubTexture name="skeeboGRABBED0027" x="2464" y="805" width="612" height="727" frameX="-106" frameY="0" frameWidth="2214" frameHeight="863"/>
	<SubTexture name="skeeboGRABBED0028" x="2464" y="805" width="612" height="727" frameX="-106" frameY="0" frameWidth="2214" frameHeight="863"/>
	<SubTexture name="skeeboGRABBED0029" x="2464" y="805" width="612" height="727" frameX="-106" frameY="0" frameWidth="2214" frameHeight="863"/>
	<SubTexture name="skeeboGRABBED0030" x="2464" y="805" width="612" height="727" frameX="-106" frameY="0" frameWidth="2214" frameHeight="863"/>
	<SubTexture name="skeeboGRABBED0031" x="2464" y="805" width="612" height="727" frameX="-106" frameY="0" frameWidth="2214" frameHeight="863"/>
	<SubTexture name="skeeboGRABBED0032" x="2464" y="805" width="612" height="727" frameX="-106" frameY="0" frameWidth="2214" frameHeight="863"/>
	<SubTexture name="skeeboGRABBED0033" x="2464" y="805" width="612" height="727" frameX="-106" frameY="0" frameWidth="2214" frameHeight="863"/>
	<SubTexture name="skeeboGRABBED0034" x="2464" y="805" width="612" height="727" frameX="-106" frameY="0" frameWidth="2214" frameHeight="863"/>
	<SubTexture name="skeeboGRABBED0035" x="2464" y="805" width="612" height="727" frameX="-106" frameY="0" frameWidth="2214" frameHeight="863"/>
	<SubTexture name="skeeboGRABBED0036" x="2464" y="805" width="612" height="727" frameX="-106" frameY="0" frameWidth="2214" frameHeight="863"/>
	<SubTexture name="skeeboGRABBED0037" x="2464" y="805" width="612" height="727" frameX="-106" frameY="0" frameWidth="2214" frameHeight="863"/>
	<SubTexture name="skeeboGRABBED0038" x="2464" y="805" width="612" height="727" frameX="-106" frameY="0" frameWidth="2214" frameHeight="863"/>
	<SubTexture name="skeeboGRABBED0039" x="2464" y="805" width="612" height="727" frameX="-106" frameY="0" frameWidth="2214" frameHeight="863"/>
	<SubTexture name="skeeboGRABBED0040" x="1848" y="805" width="612" height="727" frameX="-106" frameY="0" frameWidth="2214" frameHeight="863"/>
	<SubTexture name="skeeboGRABBED0041" x="1848" y="805" width="612" height="727" frameX="-106" frameY="0" frameWidth="2214" frameHeight="863"/>
	<SubTexture name="skeeboGRABBED0042" x="1848" y="805" width="612" height="727" frameX="-106" frameY="0" frameWidth="2214" frameHeight="863"/>
	<SubTexture name="skeeboGRABBED0043" x="3080" y="805" width="612" height="727" frameX="-106" frameY="-5" frameWidth="2214" frameHeight="863"/>
	<SubTexture name="skeeboGRABBED0044" x="3080" y="805" width="612" height="727" frameX="-106" frameY="-5" frameWidth="2214" frameHeight="863"/>
	<SubTexture name="skeeboGRABBED0045" x="3696" y="805" width="612" height="727" frameX="-106" frameY="-28" frameWidth="2214" frameHeight="863"/>
	<SubTexture name="skeeboGRABBED0046" x="3696" y="805" width="612" height="727" frameX="-106" frameY="-28" frameWidth="2214" frameHeight="863"/>
	<SubTexture name="skeeboGRABBED0047" x="4312" y="805" width="612" height="735" frameX="-106" frameY="-8" frameWidth="2214" frameHeight="863"/>
	<SubTexture name="skeeboGRABBED0048" x="4928" y="805" width="612" height="735" frameX="-106" frameY="-8" frameWidth="2214" frameHeight="863"/>
	<SubTexture name="skeeboGRABBED0049" x="5544" y="805" width="612" height="729" frameX="-106" frameY="-5" frameWidth="2214" frameHeight="863"/>
	<SubTexture name="skeeboGRABBED0050" x="6160" y="805" width="612" height="729" frameX="-106" frameY="-5" frameWidth="2214" frameHeight="863"/>
	<SubTexture name="skeeboGRABBED0051" x="6776" y="805" width="612" height="728" frameX="-106" frameY="-2" frameWidth="2214" frameHeight="863"/>
	<SubTexture name="skeeboGRABBED0052" x="6776" y="805" width="612" height="728" frameX="-106" frameY="-2" frameWidth="2214" frameHeight="863"/>
	<SubTexture name="skeeboGRABBED0053" x="7392" y="805" width="612" height="728" frameX="-106" frameY="-2" frameWidth="2214" frameHeight="863"/>
	<SubTexture name="skeeboGRABBED0054" x="0" y="1544" width="612" height="731" frameX="-106" frameY="-8" frameWidth="2214" frameHeight="863"/>
	<SubTexture name="skeeboGRABBED0055" x="616" y="1544" width="612" height="731" frameX="-106" frameY="-8" frameWidth="2214" frameHeight="863"/>
	<SubTexture name="skeeboGRABBED0056" x="1232" y="1544" width="612" height="730" frameX="-106" frameY="-37" frameWidth="2214" frameHeight="863"/>
	<SubTexture name="skeeboGRABBED0057" x="1232" y="1544" width="612" height="730" frameX="-106" frameY="-37" frameWidth="2214" frameHeight="863"/>
	<SubTexture name="skeeboGRABBED0058" x="1848" y="1544" width="612" height="727" frameX="-106" frameY="-8" frameWidth="2214" frameHeight="863"/>
	<SubTexture name="skeeboGRABBED0059" x="1848" y="1544" width="612" height="727" frameX="-106" frameY="-8" frameWidth="2214" frameHeight="863"/>
	<SubTexture name="skeeboGRABBED0060" x="2464" y="1544" width="612" height="727" frameX="-106" frameY="-5" frameWidth="2214" frameHeight="863"/>
	<SubTexture name="skeeboGRABBED0061" x="3080" y="1544" width="612" height="727" frameX="-106" frameY="-5" frameWidth="2214" frameHeight="863"/>
	<SubTexture name="skeeboGRABBED0062" x="3696" y="1544" width="612" height="727" frameX="-106" frameY="-5" frameWidth="2214" frameHeight="863"/>
	<SubTexture name="skeeboGRABBED0063" x="4312" y="1544" width="612" height="727" frameX="-106" frameY="-5" frameWidth="2214" frameHeight="863"/>
	<SubTexture name="skeeboGRABBED0064" x="4928" y="1544" width="612" height="727" frameX="-106" frameY="-5" frameWidth="2214" frameHeight="863"/>
	<SubTexture name="skeeboGRABBED0065" x="3080" y="805" width="612" height="727" frameX="-106" frameY="-8" frameWidth="2214" frameHeight="863"/>
	<SubTexture name="skeeboGRABBED0066" x="3080" y="805" width="612" height="727" frameX="-106" frameY="-8" frameWidth="2214" frameHeight="863"/>
	<SubTexture name="skeeboGRABBED0067" x="3696" y="805" width="612" height="727" frameX="-106" frameY="-37" frameWidth="2214" frameHeight="863"/>
	<SubTexture name="skeeboGRABBED0068" x="3696" y="805" width="612" height="727" frameX="-106" frameY="-37" frameWidth="2214" frameHeight="863"/>
	<SubTexture name="skeeboGRABBED0069" x="4312" y="805" width="612" height="735" frameX="-106" frameY="-8" frameWidth="2214" frameHeight="863"/>
	<SubTexture name="skeeboGRABBED0070" x="4928" y="805" width="612" height="735" frameX="-106" frameY="-8" frameWidth="2214" frameHeight="863"/>
	<SubTexture name="skeeboGRABBED0071" x="5544" y="805" width="612" height="729" frameX="-106" frameY="-5" frameWidth="2214" frameHeight="863"/>
	<SubTexture name="skeeboGRABBED0072" x="6160" y="805" width="612" height="729" frameX="-106" frameY="-5" frameWidth="2214" frameHeight="863"/>
	<SubTexture name="skeeboGRABBED0073" x="5544" y="1544" width="612" height="728" frameX="-106" frameY="-5" frameWidth="2214" frameHeight="863"/>
	<SubTexture name="skeeboGRABBED0074" x="5544" y="1544" width="612" height="728" frameX="-106" frameY="-5" frameWidth="2214" frameHeight="863"/>
	<SubTexture name="skeeboGRABBED0075" x="5544" y="1544" width="612" height="728" frameX="-106" frameY="-5" frameWidth="2214" frameHeight="863"/>
	<SubTexture name="skeeboGRABBED0076" x="6160" y="1544" width="612" height="731" frameX="-106" frameY="-8" frameWidth="2214" frameHeight="863"/>
	<SubTexture name="skeeboGRABBED0077" x="6160" y="1544" width="612" height="731" frameX="-106" frameY="-8" frameWidth="2214" frameHeight="863"/>
	<SubTexture name="skeeboGRABBED0078" x="6776" y="1544" width="612" height="730" frameX="-106" frameY="-37" frameWidth="2214" frameHeight="863"/>
	<SubTexture name="skeeboGRABBED0079" x="6776" y="1544" width="612" height="730" frameX="-106" frameY="-37" frameWidth="2214" frameHeight="863"/>
	<SubTexture name="skeeboGRABBED0080" x="7392" y="1544" width="612" height="727" frameX="-106" frameY="-8" frameWidth="2214" frameHeight="863"/>
	<SubTexture name="skeeboGRABBED0081" x="7392" y="1544" width="612" height="727" frameX="-106" frameY="-8" frameWidth="2214" frameHeight="863"/>
	<SubTexture name="skeeboGRABBED0082" x="0" y="2279" width="612" height="727" frameX="-106" frameY="-5" frameWidth="2214" frameHeight="863"/>
	<SubTexture name="skeeboGRABBED0083" x="0" y="2279" width="612" height="727" frameX="-106" frameY="-5" frameWidth="2214" frameHeight="863"/>
	<SubTexture name="skeeboGRABBED0084" x="616" y="2279" width="612" height="727" frameX="-106" frameY="-5" frameWidth="2214" frameHeight="863"/>
	<SubTexture name="skeeboGRABBED0085" x="616" y="2279" width="612" height="727" frameX="-106" frameY="-5" frameWidth="2214" frameHeight="863"/>
	<SubTexture name="skeeboGRABBED0086" x="616" y="2279" width="612" height="727" frameX="-106" frameY="-5" frameWidth="2214" frameHeight="863"/>
	<SubTexture name="skeeboGRABBED0087" x="1232" y="2279" width="612" height="727" frameX="-106" frameY="-8" frameWidth="2214" frameHeight="863"/>
	<SubTexture name="skeeboGRABBED0088" x="1232" y="2279" width="612" height="727" frameX="-106" frameY="-8" frameWidth="2214" frameHeight="863"/>
	<SubTexture name="skeeboGRABBED0089" x="1848" y="2279" width="612" height="727" frameX="-106" frameY="-37" frameWidth="2214" frameHeight="863"/>
	<SubTexture name="skeeboGRABBED0090" x="1848" y="2279" width="612" height="727" frameX="-106" frameY="-37" frameWidth="2214" frameHeight="863"/>
	<SubTexture name="skeeboGRABBED0091" x="2464" y="2279" width="612" height="735" frameX="-106" frameY="-8" frameWidth="2214" frameHeight="863"/>
	<SubTexture name="skeeboGRABBED0092" x="2464" y="2279" width="612" height="735" frameX="-106" frameY="-8" frameWidth="2214" frameHeight="863"/>
	<SubTexture name="skeeboGRABBED0093" x="3080" y="2279" width="612" height="729" frameX="-106" frameY="-5" frameWidth="2214" frameHeight="863"/>
	<SubTexture name="skeeboGRABBED0094" x="3080" y="2279" width="612" height="729" frameX="-106" frameY="-5" frameWidth="2214" frameHeight="863"/>
	<SubTexture name="skeeboGRABBED0095" x="3696" y="2279" width="612" height="728" frameX="-106" frameY="-5" frameWidth="2214" frameHeight="863"/>
	<SubTexture name="skeeboGRABBED0096" x="3696" y="2279" width="612" height="728" frameX="-106" frameY="-5" frameWidth="2214" frameHeight="863"/>
	<SubTexture name="skeeboGRABBED0097" x="3696" y="2279" width="612" height="728" frameX="-106" frameY="-5" frameWidth="2214" frameHeight="863"/>
	<SubTexture name="skeeboGRABBED0098" x="4312" y="2279" width="613" height="730" frameX="-103" frameY="-5" frameWidth="2214" frameHeight="863"/>
	<SubTexture name="skeeboGRABBED0099" x="4312" y="2279" width="613" height="730" frameX="-103" frameY="-5" frameWidth="2214" frameHeight="863"/>
	<SubTexture name="skeeboGRABBED0100" x="4929" y="2279" width="613" height="728" frameX="-74" frameY="-5" frameWidth="2214" frameHeight="863"/>
	<SubTexture name="skeeboGRABBED0101" x="4929" y="2279" width="613" height="728" frameX="-74" frameY="-5" frameWidth="2214" frameHeight="863"/>
	<SubTexture name="skeeboGRABBED0102" x="5546" y="2279" width="613" height="727" frameX="-17" frameY="-5" frameWidth="2214" frameHeight="863"/>
	<SubTexture name="skeeboGRABBED0103" x="5546" y="2279" width="613" height="727" frameX="-17" frameY="-5" frameWidth="2214" frameHeight="863"/>
	<SubTexture name="skeeboGRABBED0104" x="6163" y="2279" width="613" height="727" frameX="-3" frameY="-5" frameWidth="2214" frameHeight="863"/>
	<SubTexture name="skeeboGRABBED0105" x="6163" y="2279" width="613" height="727" frameX="-3" frameY="-5" frameWidth="2214" frameHeight="863"/>
	<SubTexture name="skeeboGRABBED0106" x="6780" y="2279" width="613" height="727" frameX="0" frameY="-5" frameWidth="2214" frameHeight="863"/>
	<SubTexture name="skeeboGRABBED0107" x="6780" y="2279" width="613" height="727" frameX="0" frameY="-5" frameWidth="2214" frameHeight="863"/>
	<SubTexture name="skeeboGRABBED0108" x="6780" y="2279" width="613" height="727" frameX="-3" frameY="-5" frameWidth="2214" frameHeight="863"/>
	<SubTexture name="skeeboGRABBED0109" x="0" y="3018" width="819" height="723" frameX="-117" frameY="-9" frameWidth="2214" frameHeight="863"/>
	<SubTexture name="skeeboGRABBED0110" x="823" y="3018" width="1048" height="723" frameX="-338" frameY="-9" frameWidth="2214" frameHeight="863"/>
	<SubTexture name="skeeboGRABBED0111" x="1875" y="3018" width="1048" height="723" frameX="-594" frameY="-9" frameWidth="2214" frameHeight="863"/>
	<SubTexture name="skeeboGRABBED0112" x="2927" y="3018" width="1102" height="723" frameX="-798" frameY="-9" frameWidth="2214" frameHeight="863"/>
	<SubTexture name="skeeboGRABBED0113" x="4033" y="3018" width="1001" height="723" frameX="-1213" frameY="-9" frameWidth="2214" frameHeight="863"/>
	<SubTexture name="skeeboGRABBED0114" x="4033" y="3018" width="1001" height="723" frameX="-1213" frameY="-9" frameWidth="2214" frameHeight="863"/>
	<SubTexture name="skeeboGRABBED0115" x="4033" y="3018" width="1001" height="723" frameX="-1213" frameY="-9" frameWidth="2214" frameHeight="863"/>
	<SubTexture name="skeeboGRABBED0116" x="4033" y="3018" width="1001" height="723" frameX="-1213" frameY="-9" frameWidth="2214" frameHeight="863"/>
	<SubTexture name="skeeboGRABBED0117" x="4033" y="3018" width="1001" height="723" frameX="-1213" frameY="-9" frameWidth="2214" frameHeight="863"/>
	<SubTexture name="skeeboGRABBED0118" x="4033" y="3018" width="1001" height="723" frameX="-1213" frameY="-9" frameWidth="2214" frameHeight="863"/>
	<SubTexture name="skeeboGRABBED0119" x="4033" y="3018" width="1001" height="723" frameX="-1213" frameY="-9" frameWidth="2214" frameHeight="863"/>
	<SubTexture name="skeeboGRABBED0120" x="4033" y="3018" width="1001" height="723" frameX="-1213" frameY="-9" frameWidth="2214" frameHeight="863"/>
	<SubTexture name="skeeboGRABBED0121" x="4033" y="3018" width="1001" height="723" frameX="-1213" frameY="-9" frameWidth="2214" frameHeight="863"/>
	<SubTexture name="skeeboGRABBED0122" x="4033" y="3018" width="1001" height="723" frameX="-1213" frameY="-9" frameWidth="2214" frameHeight="863"/>
	<SubTexture name="skeeboGRABBED0123" x="4033" y="3018" width="1001" height="723" frameX="-1213" frameY="-9" frameWidth="2214" frameHeight="863"/>
	<SubTexture name="skeeboGRABBED0124" x="4033" y="3018" width="1001" height="723" frameX="-1213" frameY="-9" frameWidth="2214" frameHeight="863"/>
	<SubTexture name="skeeboGRABBED0125" x="4033" y="3018" width="1001" height="723" frameX="-1213" frameY="-9" frameWidth="2214" frameHeight="863"/>
	<SubTexture name="skeeboGRABBED0126" x="4033" y="3018" width="1001" height="723" frameX="-1213" frameY="-9" frameWidth="2214" frameHeight="863"/>
	<SubTexture name="skeeboGRABBED0127" x="4033" y="3018" width="1001" height="723" frameX="-1213" frameY="-9" frameWidth="2214" frameHeight="863"/>
	<SubTexture name="skeeboGRABBED0128" x="4033" y="3018" width="1001" height="723" frameX="-1213" frameY="-9" frameWidth="2214" frameHeight="863"/>
	<SubTexture name="skeeboGRABBED0129" x="4033" y="3018" width="1001" height="723" frameX="-1213" frameY="-9" frameWidth="2214" frameHeight="863"/>
	<SubTexture name="skeeboGRABBED0130" x="4033" y="3018" width="1001" height="723" frameX="-1213" frameY="-9" frameWidth="2214" frameHeight="863"/>
	<SubTexture name="skeeboGRABBED0131" x="4033" y="3018" width="1001" height="723" frameX="-1213" frameY="-9" frameWidth="2214" frameHeight="863"/>
	<SubTexture name="skeeboGRABBED0132" x="4033" y="3018" width="1001" height="723" frameX="-1213" frameY="-9" frameWidth="2214" frameHeight="863"/>
	<SubTexture name="skeeboGRABBED0133" x="4033" y="3018" width="1001" height="723" frameX="-1213" frameY="-9" frameWidth="2214" frameHeight="863"/>
	<SubTexture name="skeeboGRABBED0134" x="4033" y="3018" width="1001" height="723" frameX="-1213" frameY="-9" frameWidth="2214" frameHeight="863"/>
	<SubTexture name="skeeboGRABBED0135" x="4033" y="3018" width="1001" height="723" frameX="-1213" frameY="-9" frameWidth="2214" frameHeight="863"/>
	<SubTexture name="skeeboGRABBED0136" x="4033" y="3018" width="1001" height="723" frameX="-1213" frameY="-9" frameWidth="2214" frameHeight="863"/>
	<SubTexture name="skeeboGRABBED0137" x="4033" y="3018" width="1001" height="723" frameX="-1213" frameY="-9" frameWidth="2214" frameHeight="863"/>
	<SubTexture name="skeeboGRABBED0138" x="4033" y="3018" width="1001" height="723" frameX="-1213" frameY="-9" frameWidth="2214" frameHeight="863"/>
	<SubTexture name="skeeboGRABBED0139" x="4033" y="3018" width="1001" height="723" frameX="-1213" frameY="-9" frameWidth="2214" frameHeight="863"/>
	<SubTexture name="skeeboGRABBED0140" x="4033" y="3018" width="1001" height="723" frameX="-1213" frameY="-9" frameWidth="2214" frameHeight="863"/>
	<SubTexture name="skeeboGRABBED0141" x="4033" y="3018" width="1001" height="723" frameX="-1213" frameY="-9" frameWidth="2214" frameHeight="863"/>
	<SubTexture name="skeeboGRABBED0142" x="4033" y="3018" width="1001" height="723" frameX="-1213" frameY="-9" frameWidth="2214" frameHeight="863"/>
	<SubTexture name="skeeboGRABBED0143" x="4033" y="3018" width="1001" height="723" frameX="-1213" frameY="-9" frameWidth="2214" frameHeight="863"/>
	<SubTexture name="skeeboGRABBED0144" x="4033" y="3018" width="1001" height="723" frameX="-1213" frameY="-9" frameWidth="2214" frameHeight="863"/>
	<SubTexture name="skeeboGRABBED0145" x="4033" y="3018" width="1001" height="723" frameX="-1213" frameY="-9" frameWidth="2214" frameHeight="863"/>
	<SubTexture name="skeeboGRABBED0146" x="4033" y="3018" width="1001" height="723" frameX="-1213" frameY="-9" frameWidth="2214" frameHeight="863"/>
	<SubTexture name="skeeboGRABBED0147" x="4033" y="3018" width="1001" height="723" frameX="-1213" frameY="-9" frameWidth="2214" frameHeight="863"/>
	<SubTexture name="skeeboGRABBED0148" x="4033" y="3018" width="1001" height="723" frameX="-1213" frameY="-9" frameWidth="2214" frameHeight="863"/>
	<SubTexture name="skeeboGRABBED0149" x="4033" y="3018" width="1001" height="723" frameX="-1213" frameY="-9" frameWidth="2214" frameHeight="863"/>
	<SubTexture name="skeeboGRABBED0150" x="4033" y="3018" width="1001" height="723" frameX="-1213" frameY="-9" frameWidth="2214" frameHeight="863"/>
	<SubTexture name="skeeboGRABBED0151" x="4033" y="3018" width="1001" height="723" frameX="-1213" frameY="-9" frameWidth="2214" frameHeight="863"/>
	<SubTexture name="skeeboGRABBED0152" x="4033" y="3018" width="1001" height="723" frameX="-1213" frameY="-9" frameWidth="2214" frameHeight="863"/>
	<SubTexture name="skeeboGRABBED0153" x="4033" y="3018" width="1001" height="723" frameX="-1213" frameY="-9" frameWidth="2214" frameHeight="863"/>
	<SubTexture name="skeeboGRABBED0154" x="4033" y="3018" width="1001" height="723" frameX="-1213" frameY="-9" frameWidth="2214" frameHeight="863"/>
	<SubTexture name="skeeboGRABBED0155" x="4033" y="3018" width="1001" height="723" frameX="-1213" frameY="-9" frameWidth="2214" frameHeight="863"/>
	<SubTexture name="skeeboGRABBED0156" x="4033" y="3018" width="1001" height="723" frameX="-1213" frameY="-9" frameWidth="2214" frameHeight="863"/>
	<SubTexture name="skeeboGRABBED0157" x="4033" y="3018" width="1001" height="723" frameX="-1213" frameY="-9" frameWidth="2214" frameHeight="863"/>
	<SubTexture name="skeeboGRABBED0158" x="4033" y="3018" width="1001" height="723" frameX="-1213" frameY="-9" frameWidth="2214" frameHeight="863"/>
	<SubTexture name="skeeboGRABBED0159" x="4033" y="3018" width="1001" height="723" frameX="-1213" frameY="-9" frameWidth="2214" frameHeight="863"/>
	<SubTexture name="skeeboGRABBED0160" x="4033" y="3018" width="1001" height="723" frameX="-1213" frameY="-9" frameWidth="2214" frameHeight="863"/>
	<SubTexture name="skeeboGRABBED0161" x="4033" y="3018" width="1001" height="723" frameX="-1213" frameY="-9" frameWidth="2214" frameHeight="863"/>
	<SubTexture name="skeeboGRABBED0162" x="4033" y="3018" width="1001" height="723" frameX="-1213" frameY="-9" frameWidth="2214" frameHeight="863"/>
	<SubTexture name="skeeboGRABBED0163" x="4033" y="3018" width="1001" height="723" frameX="-1213" frameY="-9" frameWidth="2214" frameHeight="863"/>
	<SubTexture name="skeeboGRABBED0164" x="4033" y="3018" width="1001" height="723" frameX="-1213" frameY="-9" frameWidth="2214" frameHeight="863"/>
	<SubTexture name="skeeboGRABBED0165" x="4033" y="3018" width="1001" height="723" frameX="-1213" frameY="-9" frameWidth="2214" frameHeight="863"/>
	<SubTexture name="skeeboGRABBED0166" x="4033" y="3018" width="1001" height="723" frameX="-1213" frameY="-9" frameWidth="2214" frameHeight="863"/>
	<SubTexture name="skeeboGRABBED0167" x="4033" y="3018" width="1001" height="723" frameX="-1213" frameY="-9" frameWidth="2214" frameHeight="863"/>
	<SubTexture name="skeeboGRABBED0168" x="4033" y="3018" width="1001" height="723" frameX="-1213" frameY="-9" frameWidth="2214" frameHeight="863"/>
	<SubTexture name="skeeboGRABBED0169" x="4033" y="3018" width="1001" height="723" frameX="-1213" frameY="-9" frameWidth="2214" frameHeight="863"/>
	<SubTexture name="skeeboGRABBED0170" x="4033" y="3018" width="1001" height="723" frameX="-1213" frameY="-9" frameWidth="2214" frameHeight="863"/>
	<SubTexture name="skeeboGRABBED0171" x="4033" y="3018" width="1001" height="723" frameX="-1213" frameY="-9" frameWidth="2214" frameHeight="863"/>
	<SubTexture name="skeeboGRABBED0172" x="4033" y="3018" width="1001" height="723" frameX="-1213" frameY="-9" frameWidth="2214" frameHeight="863"/>
	<SubTexture name="skeeboGRABBED0173" x="4033" y="3018" width="1001" height="723" frameX="-1213" frameY="-9" frameWidth="2214" frameHeight="863"/>
	<SubTexture name="skeeboGRABBED0174" x="4033" y="3018" width="1001" height="723" frameX="-1213" frameY="-9" frameWidth="2214" frameHeight="863"/>
	<SubTexture name="skeeboGRABBED0175" x="4033" y="3018" width="1001" height="723" frameX="-1213" frameY="-9" frameWidth="2214" frameHeight="863"/>
	<SubTexture name="skeeboGRABBED0176" x="4033" y="3018" width="1001" height="723" frameX="-1213" frameY="-9" frameWidth="2214" frameHeight="863"/>
	<SubTexture name="skeeboGRABBED0177" x="4033" y="3018" width="1001" height="723" frameX="-1213" frameY="-9" frameWidth="2214" frameHeight="863"/>
	<SubTexture name="skeeboGRABBED0178" x="4033" y="3018" width="1001" height="723" frameX="-1213" frameY="-9" frameWidth="2214" frameHeight="863"/>
	<SubTexture name="skeeboGRABBED0179" x="4033" y="3018" width="1001" height="723" frameX="-1213" frameY="-9" frameWidth="2214" frameHeight="863"/>
	<SubTexture name="skeeboGRABBED0180" x="4033" y="3018" width="1001" height="723" frameX="-1213" frameY="-9" frameWidth="2214" frameHeight="863"/>
	<SubTexture name="skeeboGRABBED0181" x="4033" y="3018" width="1001" height="723" frameX="-1213" frameY="-9" frameWidth="2214" frameHeight="863"/>
	<SubTexture name="skeeboGRABBED0182" x="4033" y="3018" width="1001" height="723" frameX="-1213" frameY="-9" frameWidth="2214" frameHeight="863"/>
	<SubTexture name="skeeboGRABBED0183" x="4033" y="3018" width="1001" height="723" frameX="-1213" frameY="-9" frameWidth="2214" frameHeight="863"/>
	<SubTexture name="skeeboGRABBED0184" x="4033" y="3018" width="1001" height="723" frameX="-1213" frameY="-9" frameWidth="2214" frameHeight="863"/>
	<SubTexture name="skeeboGRABBED0185" x="4033" y="3018" width="1001" height="723" frameX="-1213" frameY="-9" frameWidth="2214" frameHeight="863"/>
	<SubTexture name="skeeboGRABBED0186" x="4033" y="3018" width="1001" height="723" frameX="-1213" frameY="-9" frameWidth="2214" frameHeight="863"/>
	<SubTexture name="skeeboGRABBED0187" x="4033" y="3018" width="1001" height="723" frameX="-1213" frameY="-9" frameWidth="2214" frameHeight="863"/>
	<SubTexture name="skeeboGRABBED0188" x="4033" y="3018" width="1001" height="723" frameX="-1213" frameY="-9" frameWidth="2214" frameHeight="863"/>
	<SubTexture name="skeeboGRABBED0189" x="4033" y="3018" width="1001" height="723" frameX="-1213" frameY="-9" frameWidth="2214" frameHeight="863"/>
	<SubTexture name="skeeboGRABBED0190" x="4033" y="3018" width="1001" height="723" frameX="-1213" frameY="-9" frameWidth="2214" frameHeight="863"/>
	<SubTexture name="skeeboGRABBED0191" x="4033" y="3018" width="1001" height="723" frameX="-1213" frameY="-9" frameWidth="2214" frameHeight="863"/>
	<SubTexture name="skeeboGRABBED0192" x="4033" y="3018" width="1001" height="723" frameX="-1213" frameY="-9" frameWidth="2214" frameHeight="863"/>
	<SubTexture name="skeeboGRABBED0193" x="4033" y="3018" width="1001" height="723" frameX="-1213" frameY="-9" frameWidth="2214" frameHeight="863"/>
	<SubTexture name="skeeboGRABBED0194" x="4033" y="3018" width="1001" height="723" frameX="-1213" frameY="-9" frameWidth="2214" frameHeight="863"/>
	<SubTexture name="skeeboGRABBED0195" x="4033" y="3018" width="1001" height="723" frameX="-1213" frameY="-9" frameWidth="2214" frameHeight="863"/>
	<SubTexture name="skeeboGRABBED0196" x="4033" y="3018" width="1001" height="723" frameX="-1213" frameY="-9" frameWidth="2214" frameHeight="863"/>
	<SubTexture name="skeeboGRABBED0197" x="4033" y="3018" width="1001" height="723" frameX="-1213" frameY="-9" frameWidth="2214" frameHeight="863"/>
	<SubTexture name="skeeboGRABBED0198" x="4033" y="3018" width="1001" height="723" frameX="-1213" frameY="-9" frameWidth="2214" frameHeight="863"/>
	<SubTexture name="skeeboGRABBED0199" x="4033" y="3018" width="1001" height="723" frameX="-1213" frameY="-9" frameWidth="2214" frameHeight="863"/>
	<SubTexture name="skeeboGRABBED0200" x="4033" y="3018" width="1001" height="723" frameX="-1213" frameY="-9" frameWidth="2214" frameHeight="863"/>
	<SubTexture name="skeeboGRABBED0201" x="4033" y="3018" width="1001" height="723" frameX="-1213" frameY="-9" frameWidth="2214" frameHeight="863"/>
	<SubTexture name="skeeboGRABBED0202" x="4033" y="3018" width="1001" height="723" frameX="-1213" frameY="-9" frameWidth="2214" frameHeight="863"/>
	<SubTexture name="skeeboGRABBED0203" x="4033" y="3018" width="1001" height="723" frameX="-1213" frameY="-9" frameWidth="2214" frameHeight="863"/>
	<SubTexture name="skeeboGRABBED0204" x="4033" y="3018" width="1001" height="723" frameX="-1213" frameY="-9" frameWidth="2214" frameHeight="863"/>
	<SubTexture name="skeeboGRABBED0205" x="4033" y="3018" width="1001" height="723" frameX="-1213" frameY="-9" frameWidth="2214" frameHeight="863"/>
	<SubTexture name="skeeboGRABBED0206" x="4033" y="3018" width="1001" height="723" frameX="-1213" frameY="-9" frameWidth="2214" frameHeight="863"/>
</TextureAtlas>
